{"version": 0.6, "generator": "Overpass API 0.7.62.8 e802775f", "osm3s": {"timestamp_osm_base": "2025-12-06T18:32:45Z", "copyright": "The data included in this document is from www.openstreetmap.org. The data is made available under ODbL."}, "elements": [{"type": "node", "id": 2608877707, "lat": 49.0783724, "lon": -107.9227275}, {"type": "node", "id": 2608877725, "lat": 49.0816726, "lon": -107.922442}, {"type": "node", "id": 2608877729, "lat": 49.0821277, "lon": -107.9222358}, {"type": "node", "id": 2608877731, "lat": 49.0828053, "lon": -107.9217688}, {"type": "node", "id": 2608877732, "lat": 49.0830682, "lon": -107.9216884}, {"type": "node", "id": 2608877733, "lat": 49.0834818, "lon": -107.921699}, {"type": "node", "id": 2608877735, "lat": 49.0839424, "lon": -107.9315608}, {"type": "node", "id": 2608877736, "lat": 49.0840177, "lon": -107.9218537}, {"type": "node", "id": 2608877737, "lat": 49.0843968, "lon": -107.9218075}, {"type": "node", "id": 2608877738, "lat": 49.0847358, "lon": -107.9215671}, {"type": "node", "id": 2608877739, "lat": 49.0853163, "lon": -107.9210259}, {"type": "node", "id": 2608877740, "lat": 49.0856999, "lon": -107.9208019}, {"type": "node", "id": 2608877741, "lat": 49.086254, "lon": -107.9242891}, {"type": "node", "id": 2608877742, "lat": 49.0862891, "lon": -107.9241788}, {"type": "node", "id": 2608877743, "lat": 49.0866644, "lon": -107.9232146}, {"type": "node", "id": 2608877756, "lat": 49.0871044, "lon": -107.920761}, {"type": "node", "id": 2608877760, "lat": 49.0871262, "lon": -107.8985025}, {"type": "node", "id": 2608877763, "lat": 49.0871814, "lon": -107.9223409}, {"type": "node", "id": 2608877764, "lat": 49.0876918, "lon": -107.921727}, {"type": "node", "id": 2608877765, "lat": 49.0884351, "lon": -107.9211542}, {"type": "node", "id": 2608877766, "lat": 49.089443, "lon": -107.9207887}, {"type": "node", "id": 2608877793, "lat": 49.1162145, "lon": -107.8984715}, {"type": "node", "id": 2608877799, "lat": 49.1162555, "lon": -107.9207467}, {"type": "node", "id": 2608877802, "lat": 49.1162578, "lon": -107.876256}, {"type": "node", "id": 2608877866, "lat": 49.125, "lon": -107.8984821}, {"type": "node", "id": 2608877894, "lat": 49.1322274, "lon": -107.8762619}, {"type": "node", "id": 2608877900, "lat": 49.1384985, "lon": -107.8762548}, {"type": "node", "id": 2608877901, "lat": 49.1387911, "lon": -107.8760661}, {"type": "node", "id": 2608877902, "lat": 49.1391502, "lon": -107.8753738}, {"type": "node", "id": 2608877903, "lat": 49.1394239, "lon": -107.8752251}, {"type": "node", "id": 2608877904, "lat": 49.1402643, "lon": -107.8754383}, {"type": "node", "id": 2608877907, "lat": 49.1410872, "lon": -107.8759934}, {"type": "node", "id": 2608877914, "lat": 49.1417206, "lon": -107.8762083}, {"type": "node", "id": 2608877922, "lat": 49.1422423, "lon": -107.8762111}, {"type": "node", "id": 2608877975, "lat": 49.1453719, "lon": -107.876269}, {"type": "node", "id": 2608878035, "lat": 49.1540211, "lon": -107.8540415}, {"type": "node", "id": 2608878108, "lat": 49.1744613, "lon": -107.8540784}, {"type": "node", "id": 2608878111, "lat": 49.1744709, "lon": -107.8445831}, {"type": "node", "id": 2608878118, "lat": 49.1744886, "lon": -107.8222441}, {"type": "node", "id": 2608878127, "lat": 49.1761057, "lon": -107.8446906}, {"type": "node", "id": 2608878128, "lat": 49.1775027, "lon": -107.8222372}, {"type": "node", "id": 2608878129, "lat": 49.1776807, "lon": -107.822316}, {"type": "node", "id": 2608878130, "lat": 49.178055, "lon": -107.8228313}, {"type": "node", "id": 2608878131, "lat": 49.1783768, "lon": -107.8229182}, {"type": "node", "id": 2608878132, "lat": 49.1789278, "lon": -107.8228261}, {"type": "node", "id": 2608878133, "lat": 49.1796161, "lon": -107.8222751}, {"type": "node", "id": 2608878134, "lat": 49.1800407, "lon": -107.8222032}, {"type": "node", "id": 2608878140, "lat": 49.183423, "lon": -107.8445751}, {"type": "node", "id": 2608878148, "lat": 49.1879807, "lon": -107.8447267}, {"type": "node", "id": 2608878186, "lat": 49.2035927, "lon": -107.8446343}, {"type": "node", "id": 2608878187, "lat": 49.203593, "lon": -107.8222675}, {"type": "way", "id": 255159039, "nodes": [2608877894, 2608877900, 2608877901, 2608877902, 2608877903, 2608877904, 2608877907, 2608877914, 2608877922, 2608877975], "tags": {"highway": "track", "lanes": "1", "source": "NRCan-CanVec-10.0", "surface": "dirt"}}, {"type": "way", "id": 255159042, "nodes": [2608877707, 2608877725, 2608877729, 2608877731, 2608877732, 2608877733, 2608877736, 2608877737, 2608877738, 2608877739, 2608877740, 2608877756], "tags": {"highway": "unclassified", "lanes": "2", "maxspeed": "80", "source": "NRCan-CanVec-10.0", "surface": "gravel"}}, {"type": "way", "id": 255159053, "nodes": [2608878035, 2608878108], "tags": {"highway": "track", "lanes": "1", "source": "NRCan-CanVec-10.0", "surface": "dirt"}}, {"type": "way", "id": 255159054, "nodes": [2608878108, 2608878111], "tags": {"highway": "track", "lanes": "1", "source": "NRCan-CanVec-10.0", "surface": "dirt"}}, {"type": "way", "id": 255159068, "nodes": [2608877793, 2608877866], "tags": {"highway": "unclassified", "lanes": "2", "maxspeed": "80", "source": "NRCan-CanVec-10.0", "surface": "dirt"}}, {"type": "way", "id": 255159088, "nodes": [2608877766, 2608877799], "tags": {"highway": "unclassified", "lanes": "2", "maxspeed": "80", "source": "NRCan-CanVec-10.0", "surface": "gravel"}}, {"type": "way", "id": 255159094, "nodes": [2608877756, 2608877760], "tags": {"highway": "unclassified", "lanes": "2", "maxspeed": "80", "source": "NRCan-CanVec-10.0", "surface": "gravel"}}, {"type": "way", "id": 255159104, "nodes": [2608877793, 2608877802], "tags": {"highway": "unclassified", "lanes": "2", "maxspeed": "80", "source": "NRCan-CanVec-10.0", "surface": "dirt"}}, {"type": "way", "id": 255159125, "nodes": [2608878111, 2608878118], "tags": {"highway": "track", "lanes": "1", "source": "NRCan-CanVec-10.0", "surface": "dirt"}}, {"type": "way", "id": 255159156, "nodes": [2608877756, 2608877766], "tags": {"highway": "unclassified", "lanes": "2", "maxspeed": "80", "source": "NRCan-CanVec-10.0", "surface": "gravel"}}, {"type": "way", "id": 255159173, "nodes": [2608877760, 2608877793], "tags": {"highway": "unclassified", "lanes": "2", "maxspeed": "80", "source": "NRCan-CanVec-10.0", "surface": "dirt"}}, {"type": "way", "id": 255159180, "nodes": [2608877793, 2608877799], "tags": {"highway": "unclassified", "lanes": "2", "maxspeed": "80", "source": "NRCan-CanVec-10.0", "surface": "dirt"}}, {"type": "way", "id": 255159224, "nodes": [2608878111, 2608878127, 2608878140, 2608878148, 2608878186], "tags": {"highway": "track", "lanes": "1", "source": "NRCan-CanVec-10.0", "surface": "dirt"}}, {"type": "way", "id": 255159261, "nodes": [2608877735, 2608877741, 2608877742, 2608877743, 2608877763, 2608877764, 2608877765, 2608877766], "tags": {"highway": "unclassified", "lanes": "2", "maxspeed": "80", "source": "NRCan-CanVec-10.0", "surface": "gravel"}}, {"type": "way", "id": 255159264, "nodes": [2608878118, 2608878128, 2608878129, 2608878130, 2608878131, 2608878132, 2608878133, 2608878134, 2608878187], "tags": {"highway": "unclassified", "lanes": "2", "maxspeed": "80", "source": "NRCan-CanVec-10.0", "surface": "dirt"}}]}